mypythonproject_clodo/__cli__.py
mypythonproject_clodo/__init__.py
mypythonproject_clodo/another_module/__init__.py
mypythonproject_clodo/another_module/another_module.py
mypythonproject_clodo/cli/__init__.py
mypythonproject_clodo/cli/cli.py
mypythonproject_clodo/cli/hatch_build.py
mypythonproject_clodo/cli/utils.py
mypythonproject_clodo/sample_module/__init__.py
mypythonproject_clodo/sample_module/sample_module.py
mypythonproject_clodo/cli/header.json
mypythonproject_clodo/cli/help.json
mypythonproject_clodo/cli/modules.json
mypythonproject_clodo/cli/template.json
mypythonproject_clodo-1.0.0.2.dist-info/METADATA
mypythonproject_clodo-1.0.0.2.dist-info/WHEEL
mypythonproject_clodo-1.0.0.2.dist-info/entry_points.txt
mypythonproject_clodo-1.0.0.2.dist-info/licenses/LICENSE
mypythonproject_clodo-1.0.0.2.dist-info/RECORD
